textualog/__init__.py
textualog/__main__.py
textualog/__version__.py
textualog/emojis.py
textualog/loader.py
textualog/log.py
textualog/styles.py
textualog/system.py
textualog/unicodes.py
textualog/renderables/__init__.py
textualog/renderables/logrecord.py
textualog/renderables/namespace_tree.py
textualog/renderables/shortcuts.py
textualog/widgets/__init__.py
textualog/widgets/details.py
textualog/widgets/footer.py
textualog/widgets/help.py
textualog/widgets/levels.py
textualog/widgets/namespaces.py
textualog/widgets/recordinfo.py
textualog/widgets/records.py
textualog-0.1.2.dist-info/METADATA
textualog-0.1.2.dist-info/WHEEL
textualog-0.1.2.dist-info/entry_points.txt
textualog-0.1.2.dist-info/top_level.txt
textualog-0.1.2.dist-info/RECORD
