Metadata-Version: 2.1
Name: textualog
Version: 0.1.2
Summary: Display, filter and search logging messages in the terminal.
Home-page: https://github.com/rhuygen/textualog
Author: Rik Huygen
Author-email: rik.huygen@kuleuven.be
License: MIT
Platform: UNKNOWN
Classifier: License :: OSI Approved :: MIT License
Classifier: Environment :: Console
Classifier: Topic :: Utilities
Classifier: Development Status :: 3 - Alpha
Classifier: Programming Language :: Python :: 3
Classifier: Programming Language :: Python :: 3.8
Requires-Python: >=3.8.0
Requires-Dist: rich
Requires-Dist: textual
